django_my_imgur-0.0.0a3.dist-info/METADATA
django_my_imgur-0.0.0a3.dist-info/RECORD
django_my_imgur-0.0.0a3.dist-info/WHEEL
django_my_imgur-0.0.0a3.dist-info/top_level.txt
my_imgur/__init__.py
my_imgur/admin.py
my_imgur/apps.py
my_imgur/models.py
my_imgur/settings.py
my_imgur/tests.py
my_imgur/views.py
my_imgur/migrations/__init__.py
