Metadata-Version: 2.1
Name: django-my-imgur
Version: 0.0.0a3
Summary: Django and Imgur.
Home-page: https://github.com/poipoii/django-my-imgur
Author: poipoii
Author-email: earth.sama@gmail.com
License: UNKNOWN
Download-URL: https://github.com/poipoii/django-my-imgur/releases
Platform: UNKNOWN
Requires-Dist: Pillow (==5.1.0)
Requires-Dist: ppyimgur
